causality_ml/__init__.py
causality_ml/hypothesis_tests/categorical_tests.py
causality_ml/hypothesis_tests/continuous_tests.py
causality_ml/models/meta_learners.py
causality_ml/rct/rct.py
causality_ml-0.0.1.dist-info/METADATA
causality_ml-0.0.1.dist-info/WHEEL
causality_ml-0.0.1.dist-info/licenses/LICENSE
causality_ml-0.0.1.dist-info/RECORD
