Metadata-Version: 2.3
Name: causality_ml
Version: 0.0.1
Summary: Yet Another Causality Library
Project-URL: Homepage, https://github.com/EricSchles/causality
Project-URL: Issues, https://github.com/EricSchles/causality/issues
Author-email: Eric Schles <eschles3@jh.edu>
License-File: LICENSE
Classifier: License :: OSI Approved :: MIT License
Classifier: Operating System :: OS Independent
Classifier: Programming Language :: Python :: 3
Requires-Python: >=3.10
